rexi/__init__.py
rexi/rexi_api.py
rexi/solana.py
rexi_py-0.1.6.dist-info/licenses/LICENSE
rexi_py-0.1.6.dist-info/METADATA
rexi_py-0.1.6.dist-info/WHEEL
rexi_py-0.1.6.dist-info/top_level.txt
rexi_py-0.1.6.dist-info/RECORD
